{
    "meta": {
        "label": "Cosmian Server Dataset",
        "description": "Cosmian Server Dataset",
        "icon": "icon-lock"
    },
    "readable": true,
    "writable": false,
    "params": [
        {
            "name": "server_url",
            "label": "Cosmian server URL",
            "type": "STRING",
            "description": "The base URL of the Cosmian server",
            "mandatory": true,
            "defaultValue": "http://localhost:9999"
        },
        {
            "name": "dataset_name",
            "label": "Dataset Name",
            "description": "The unique name of the Dataset on the Cosmian server",
            "type": "STRING",
            "mandatory": true,
            "defaultValue": ""
        }
    ]
}
